xbout/__init__.py
xbout/_version.py
xbout/boutdataarray.py
xbout/boutdataset.py
xbout/conftest.py
xbout/fastoutput.py
xbout/geometries.py
xbout/load.py
xbout/region.py
xbout/utils.py
xbout/xarraybackend.py
xbout/calc/__init__.py
xbout/calc/turbulence.py
xbout/calc/tests/test_turbulence.py
xbout/cherab/__init__.py
xbout/cherab/grid.py
xbout/cherab/triangulate.py
xbout/plotting/__init__.py
xbout/plotting/animate.py
xbout/plotting/plotfuncs.py
xbout/plotting/utils.py
xbout/tests/__init__.py
xbout/tests/conftest.py
xbout/tests/test_against_collect.py
xbout/tests/test_animate.py
xbout/tests/test_boutdataarray.py
xbout/tests/test_boutdataset.py
xbout/tests/test_fastoutput.py
xbout/tests/test_geometries.py
xbout/tests/test_grid.py
xbout/tests/test_init.py
xbout/tests/test_load.py
xbout/tests/test_plot.py
xbout/tests/test_region.py
xbout/tests/test_utils.py
xbout/tests/utils_for_tests.py
xbout/tests/data/options/BOUT.inp
xbout/tests/data/restart/BOUT.restart.0.nc
xbout/tests/data/restart/BOUT.restart.1.nc
xbout/tests/data/restart/README.md
xbout/tests/inputs/s-alpha.inp
xbout-0.3.8.dist-info/licenses/LICENSE
xbout-0.3.8.dist-info/METADATA
xbout-0.3.8.dist-info/WHEEL
xbout-0.3.8.dist-info/entry_points.txt
xbout-0.3.8.dist-info/top_level.txt
xbout-0.3.8.dist-info/RECORD
