Metadata-Version: 2.4
Name: xbout
Version: 0.3.8
Summary: Collect data from BOUT++ runs in python using xarray
Author: John Omotani
Author-email: Thomas Nicholas <thomas.nicholas@york.ac.uk>
License:                                  Apache License
Project-URL: Source, https://github.com/boutproject/xBOUT
Project-URL: Tracker, https://github.com/boutproject/xBOUT/issues
Project-URL: Documentation, https://xbout.readthedocs.io/en/latest/
Keywords: gyrokinetics,analysis,plasma,research
Classifier: Development Status :: 3 - Alpha
Classifier: Intended Audience :: Science/Research
Classifier: Intended Audience :: Education
Classifier: Intended Audience :: Developers
Classifier: License :: OSI Approved :: Apache Software License
Classifier: Natural Language :: English
Classifier: Operating System :: POSIX :: Linux
Classifier: Programming Language :: Python :: 3.8
Classifier: Programming Language :: Python :: 3.9
Classifier: Programming Language :: Python :: 3.10
Classifier: Programming Language :: Python :: 3.11
Classifier: Topic :: Scientific/Engineering :: Visualization
Requires-Python: >=3.8
License-File: LICENSE
Requires-Dist: xarray>=2023.01.0
Requires-Dist: boutdata>=0.1.4
Requires-Dist: dask[array]>=2.10.0
Requires-Dist: gelidum>=0.5.3
Requires-Dist: natsort>=5.5.0
Requires-Dist: matplotlib!=3.3.0,!=3.3.1,!=3.3.2,>=3.1.1
Requires-Dist: animatplot-ng>=0.4.2
Requires-Dist: netcdf4>=1.4.0
Requires-Dist: Pillow>=6.1.0
Provides-Extra: calc
Requires-Dist: numpy>=1.18.0; extra == "calc"
Requires-Dist: scipy>=1.3.0; extra == "calc"
Requires-Dist: dask>=2.2.0; extra == "calc"
Requires-Dist: statsmodels>=0.10.1; extra == "calc"
Requires-Dist: xrft; extra == "calc"
Requires-Dist: xhistogram; extra == "calc"
Provides-Extra: cherab
Requires-Dist: cherab; extra == "cherab"
Provides-Extra: docs
Requires-Dist: sphinx>=5.3; extra == "docs"
Requires-Dist: sphinx-book-theme>=0.4.0rc1; extra == "docs"
Requires-Dist: sphinx_autodoc_typehints>=1.19; extra == "docs"
Provides-Extra: 3d-plot
Requires-Dist: k3d>=2.8.0; extra == "3d-plot"
Requires-Dist: mayavi>=4.7.2; extra == "3d-plot"
Requires-Dist: wand; extra == "3d-plot"
Provides-Extra: tests
Requires-Dist: pytest>=3.3.0; extra == "tests"
Requires-Dist: pytest-cov; extra == "tests"
Dynamic: license-file
